tests/__init__.py
tests/unit/__init__.py
tests/unit/test_subcommands.py
tests/unit/test_tower.py
twkit/__init__.py
twkit/cli.py
twkit/computeenvs.py
twkit/helper.py
twkit/overwrite.py
twkit/pipelines.py
twkit/tower.py
twkit/utils.py
twkit-0.3.0.dist-info/LICENSE.txt
twkit-0.3.0.dist-info/METADATA
twkit-0.3.0.dist-info/WHEEL
twkit-0.3.0.dist-info/entry_points.txt
twkit-0.3.0.dist-info/top_level.txt
twkit-0.3.0.dist-info/RECORD
