Metadata-Version: 2.1
Name: twkit
Version: 0.3.0
Summary: Automate creation of Nextflow Tower resources
Home-page: https://github.com/seqeralabs/twkit
Author: Esha Joshi, Adam Talbot, Harshil Patel
Author-email: esha.joshi@seqera.io, adam.talbot@seqera.io, harshil.patel@seqera.io
License: MIT
Keywords: nextflow,bioinformatics,workflow,pipeline,nextflow-tower
Requires-Python: >=3.8, <4
License-File: LICENSE.txt
Requires-Dist: pyyaml (>=6.0.0)
